{
  "cadence": "intraday",
  "date_range": [
    "2026-05-29",
    "2026-06-18"
  ],
  "universe_top": 200,
  "n_rows": 3085192,
  "n_features": 15,
  "n_symbols": 200,
  "results": [
    {
      "name": "probe_ret_5m_up_h15_b50",
      "signal": "feature",
      "label": "up_move_start",
      "horizon": 15,
      "n_test_ts": 147,
      "n_rows": 3080089,
      "mean_ic": 0.0018420095998357858,
      "shuffle_ic": 0.0028990347469930607,
      "edge_vs_shuffle": -0.001057025147157275,
      "nw_t": 0.09499886255083273,
      "net_per_period": 0.04467153138886838,
      "gross_per_period": 0.04670439604413194,
      "sharpe_net": 4.710896583342435,
      "breakeven_cost_bps": 150.38839597982744,
      "cost_used_bps": 1.1837841719388962,
      "predict_zero_pnl": 0.0,
      "notes": ""
    },
    {
      "name": "probe_ret_15m_up_h15_b50",
      "signal": "feature",
      "label": "up_move_start",
      "horizon": 15,
      "n_test_ts": 147,
      "n_rows": 3080089,
      "mean_ic": 0.029174841138544755,
      "shuffle_ic": -0.002073995066043251,
      "edge_vs_shuffle": 0.03124883620458801,
      "nw_t": 1.3813309839661807,
      "net_per_period": 0.029695175887242072,
      "gross_per_period": 0.031628524425643276,
      "sharpe_net": 3.1407054132225887,
      "breakeven_cost_bps": 102.86650388163984,
      "cost_used_bps": 1.1837841719388962,
      "predict_zero_pnl": 0.0,
      "notes": ""
    },
    {
      "name": "probe_ret_30m_up_h15_b50",
      "signal": "feature",
      "label": "up_move_start",
      "horizon": 15,
      "n_test_ts": 147,
      "n_rows": 3080089,
      "mean_ic": 0.005764208098693525,
      "shuffle_ic": 0.002474948815286242,
      "edge_vs_shuffle": 0.0032892592834072834,
      "nw_t": 0.27987834942421724,
      "net_per_period": -0.015058266310892215,
      "gross_per_period": -0.01311462535952332,
      "sharpe_net": -1.5244177708840123,
      "breakeven_cost_bps": -41.81353505160687,
      "cost_used_bps": 1.1837841719388962,
      "predict_zero_pnl": 0.0,
      "notes": ""
    },
    {
      "name": "probe_ret_60m_up_h15_b50",
      "signal": "feature",
      "label": "up_move_start",
      "horizon": 15,
      "n_test_ts": 147,
      "n_rows": 3080089,
      "mean_ic": 0.00379810269080504,
      "shuffle_ic": 0.0022202533710811287,
      "edge_vs_shuffle": 0.0015778493197239115,
      "nw_t": 0.17284196756730608,
      "net_per_period": -0.04714854915642765,
      "gross_per_period": -0.0455801945597864,
      "sharpe_net": -4.708014205885705,
      "breakeven_cost_bps": -197.8293881078339,
      "cost_used_bps": 1.1837841719388962,
      "predict_zero_pnl": 0.0,
      "notes": ""
    },
    {
      "name": "probe_realized_vol_5m_up_h15_b50",
      "signal": "feature",
      "label": "up_move_start",
      "horizon": 15,
      "n_test_ts": 147,
      "n_rows": 3080089,
      "mean_ic": -0.024459276747080625,
      "shuffle_ic": 0.009618964396633952,
      "edge_vs_shuffle": -0.03407824114371458,
      "nw_t": -0.897698869163938,
      "net_per_period": -0.03761067969678095,
      "gross_per_period": -0.0363574001028983,
      "sharpe_net": -3.3661650152361644,
      "breakeven_cost_bps": -179.66101694915125,
      "cost_used_bps": 1.1837841719388962,
      "predict_zero_pnl": 0.0,
      "notes": ""
    },
    {
      "name": "probe_realized_vol_30m_up_h15_b50",
      "signal": "feature",
      "label": "up_move_start",
      "horizon": 15,
      "n_test_ts": 147,
      "n_rows": 3080089,
      "mean_ic": -0.0406308373422536,
      "shuffle_ic": -0.0004888765776989512,
      "edge_vs_shuffle": -0.04014196076455465,
      "nw_t": -1.3255511885836286,
      "net_per_period": -0.06645625236602692,
      "gross_per_period": -0.06556908477676786,
      "sharpe_net": -5.772908734127832,
      "breakeven_cost_bps": -515.3666427030852,
      "cost_used_bps": 1.1837841719388962,
      "predict_zero_pnl": 0.0,
      "notes": ""
    },
    {
      "name": "probe_peak_trades_per_second_1m_up_h15_b50",
      "signal": "feature",
      "label": "up_move_start",
      "horizon": 15,
      "n_test_ts": 147,
      "n_rows": 3080089,
      "mean_ic": -0.003929718589958261,
      "shuffle_ic": -0.007364193122869091,
      "edge_vs_shuffle": 0.0034344745329108308,
      "nw_t": -0.2835324245338181,
      "net_per_period": -0.03731633128756412,
      "gross_per_period": -0.035785742868576005,
      "sharpe_net": -4.731506943339219,
      "breakeven_cost_bps": -141.36031072170755,
      "cost_used_bps": 1.1837841719388962,
      "predict_zero_pnl": 0.0,
      "notes": ""
    },
    {
      "name": "probe_inter_arrival_cv_1m_up_h15_b50",
      "signal": "feature",
      "label": "up_move_start",
      "horizon": 15,
      "n_test_ts": 147,
      "n_rows": 3080089,
      "mean_ic": -0.002516356111337798,
      "shuffle_ic": -0.00136540661224543,
      "edge_vs_shuffle": -0.001150949499092368,
      "nw_t": -0.24182020054513279,
      "net_per_period": -0.02696691674649671,
      "gross_per_period": -0.025152918310181214,
      "sharpe_net": -3.8409877810819473,
      "breakeven_cost_bps": -93.10198899703842,
      "cost_used_bps": 1.1837841719388962,
      "predict_zero_pnl": 0.0,
      "notes": ""
    },
    {
      "name": "probe_max_runup_1m_up_h15_b50",
      "signal": "feature",
      "label": "up_move_start",
      "horizon": 15,
      "n_test_ts": 147,
      "n_rows": 3080089,
      "mean_ic": -0.005110707227746198,
      "shuffle_ic": -0.006440182106011302,
      "edge_vs_shuffle": 0.0013294748782651045,
      "nw_t": -0.27787149253228727,
      "net_per_period": 0.006139145894535931,
      "gross_per_period": 0.00680272108843537,
      "sharpe_net": 0.6639851796847525,
      "breakeven_cost_bps": 50.87209302325653,
      "cost_used_bps": 1.1837841719388962,
      "predict_zero_pnl": 0.0,
      "notes": ""
    },
    {
      "name": "probe_signed_volume_15m_up_h15_b50",
      "signal": "feature",
      "label": "up_move_start",
      "horizon": 15,
      "n_test_ts": 147,
      "n_rows": 3080089,
      "mean_ic": -0.004294231121156192,
      "shuffle_ic": 0.0037110967297740217,
      "edge_vs_shuffle": -0.008005327850930213,
      "nw_t": -0.4338554359029134,
      "net_per_period": 0.02500658805928688,
      "gross_per_period": 0.02601040416166467,
      "sharpe_net": 3.8205662240931186,
      "breakeven_cost_bps": 103.75809541184105,
      "cost_used_bps": 1.1837841719388962,
      "predict_zero_pnl": 0.0,
      "notes": ""
    },
    {
      "name": "probe_trade_freq_15m_up_h15_b50",
      "signal": "feature",
      "label": "up_move_start",
      "horizon": 15,
      "n_test_ts": 147,
      "n_rows": 3080089,
      "mean_ic": -0.0013777371729622866,
      "shuffle_ic": -0.00909316372909752,
      "edge_vs_shuffle": 0.007715426556135233,
      "nw_t": -0.08092825309655942,
      "net_per_period": 0.005756338811781955,
      "gross_per_period": 0.006345395300977532,
      "sharpe_net": 0.6498776547164339,
      "breakeven_cost_bps": 78.86883615176853,
      "cost_used_bps": 1.1837841719388962,
      "predict_zero_pnl": 0.0,
      "notes": ""
    },
    {
      "name": "probe_trade_rate_accel_1m_up_h15_b50",
      "signal": "feature",
      "label": "up_move_start",
      "horizon": 15,
      "n_test_ts": 147,
      "n_rows": 3080089,
      "mean_ic": 0.001198841180155141,
      "shuffle_ic": -0.010211583934785013,
      "edge_vs_shuffle": 0.011410425114940155,
      "nw_t": 0.1242895884106162,
      "net_per_period": 0.01772945618443155,
      "gross_per_period": 0.01909335162636483,
      "sharpe_net": 2.518621154080356,
      "breakeven_cost_bps": 61.505598114320506,
      "cost_used_bps": 1.1837841719388962,
      "predict_zero_pnl": 0.0,
      "notes": ""
    },
    {
      "name": "probe_spread_bps_15m_up_h15_b50",
      "signal": "feature",
      "label": "up_move_start",
      "horizon": 15,
      "n_test_ts": 147,
      "n_rows": 3080089,
      "mean_ic": -0.029245513191815998,
      "shuffle_ic": 0.0040377535670093005,
      "edge_vs_shuffle": -0.0332832667588253,
      "nw_t": -1.4752355172850042,
      "net_per_period": -0.01722558370396873,
      "gross_per_period": -0.01644657863145258,
      "sharpe_net": -1.9273631824207618,
      "breakeven_cost_bps": -219.19999999999519,
      "cost_used_bps": 1.1837841719388962,
      "predict_zero_pnl": 0.0,
      "notes": ""
    },
    {
      "name": "probe_quote_imbalance_15m_up_h15_b50",
      "signal": "feature",
      "label": "up_move_start",
      "horizon": 15,
      "n_test_ts": 147,
      "n_rows": 3080089,
      "mean_ic": 0.017705127931109257,
      "shuffle_ic": 0.008602021957001549,
      "edge_vs_shuffle": 0.009103105974107708,
      "nw_t": 1.9264139278451278,
      "net_per_period": 0.11159983533532669,
      "gross_per_period": 0.11308523409363745,
      "sharpe_net": 18.059785092967743,
      "breakeven_cost_bps": 515.4018712042488,
      "cost_used_bps": 1.1837841719388962,
      "predict_zero_pnl": 0.0,
      "notes": ""
    },
    {
      "name": "probe_book_depth_1m_up_h15_b50",
      "signal": "feature",
      "label": "up_move_start",
      "horizon": 15,
      "n_test_ts": 147,
      "n_rows": 3080089,
      "mean_ic": -0.011753959670425092,
      "shuffle_ic": 0.0007610054271099209,
      "edge_vs_shuffle": -0.012514965097535012,
      "nw_t": -1.0045817632101848,
      "net_per_period": -0.02432427754964864,
      "gross_per_period": -0.023709483793517408,
      "sharpe_net": -3.483881665751903,
      "breakeven_cost_bps": -224.3808225403361,
      "cost_used_bps": 1.1837841719388962,
      "predict_zero_pnl": 0.0,
      "notes": ""
    },
    {
      "name": "probe_ret_5m_rev_up_h15_b50",
      "signal": "feature",
      "label": "up_move_start",
      "horizon": 15,
      "n_test_ts": 147,
      "n_rows": 3080089,
      "mean_ic": -0.0018420095998357858,
      "shuffle_ic": -0.0028990347469930607,
      "edge_vs_shuffle": 0.001057025147157275,
      "nw_t": -0.09499886255083273,
      "net_per_period": -0.047937538866394555,
      "gross_per_period": -0.04590407591608072,
      "sharpe_net": -5.038211413808657,
      "breakeven_cost_bps": -147.77327935222863,
      "cost_used_bps": 1.1837841719388962,
      "predict_zero_pnl": 0.0,
      "notes": ""
    },
    {
      "name": "probe_ret_15m_rev_up_h15_b50",
      "signal": "feature",
      "label": "up_move_start",
      "horizon": 15,
      "n_test_ts": 147,
      "n_rows": 3080089,
      "mean_ic": -0.029174841138544755,
      "shuffle_ic": 0.002073995066043251,
      "edge_vs_shuffle": -0.03124883620458801,
      "nw_t": -1.3813309839661807,
      "net_per_period": -0.033561872964044476,
      "gross_per_period": -0.031628524425643276,
      "sharpe_net": -3.5483029475426253,
      "breakeven_cost_bps": -102.86650388163984,
      "cost_used_bps": 1.1837841719388962,
      "predict_zero_pnl": 0.0,
      "notes": ""
    },
    {
      "name": "probe_ret_30m_rev_up_h15_b50",
      "signal": "feature",
      "label": "up_move_start",
      "horizon": 15,
      "n_test_ts": 147,
      "n_rows": 3080089,
      "mean_ic": -0.005764208098693525,
      "shuffle_ic": -0.002474948815286242,
      "edge_vs_shuffle": -0.0032892592834072834,
      "nw_t": -0.27987834942421724,
      "net_per_period": 0.011170984408154427,
      "gross_per_period": 0.01311462535952332,
      "sharpe_net": 1.1304530669200197,
      "breakeven_cost_bps": 41.81353505160687,
      "cost_used_bps": 1.1837841719388962,
      "predict_zero_pnl": 0.0,
      "notes": ""
    },
    {
      "name": "probe_signed_volume_15m_rev_up_h15_b50",
      "signal": "feature",
      "label": "up_move_start",
      "horizon": 15,
      "n_test_ts": 147,
      "n_rows": 3080089,
      "mean_ic": 0.004294231121156192,
      "shuffle_ic": -0.0037110967297740217,
      "edge_vs_shuffle": 0.008005327850930213,
      "nw_t": 0.4338554359029134,
      "net_per_period": -0.027014220264042453,
      "gross_per_period": -0.02601040416166467,
      "sharpe_net": -4.126345364463632,
      "breakeven_cost_bps": -103.75809541184105,
      "cost_used_bps": 1.1837841719388962,
      "predict_zero_pnl": 0.0,
      "notes": ""
    },
    {
      "name": "probe_quote_imbalance_15m_rev_up_h15_b50",
      "signal": "feature",
      "label": "up_move_start",
      "horizon": 15,
      "n_test_ts": 147,
      "n_rows": 3080089,
      "mean_ic": -0.017705127931109257,
      "shuffle_ic": -0.008602021957001549,
      "edge_vs_shuffle": -0.009103105974107708,
      "nw_t": -1.9264139278451278,
      "net_per_period": -0.11457063285194821,
      "gross_per_period": -0.11308523409363745,
      "sharpe_net": -18.5571136896612,
      "breakeven_cost_bps": -515.4018712042488,
      "cost_used_bps": 1.1837841719388962,
      "predict_zero_pnl": 0.0,
      "notes": ""
    },
    {
      "name": "probe_ret_5m_runup_h15",
      "signal": "feature",
      "label": "fwd_max_runup",
      "horizon": 15,
      "n_test_ts": 147,
      "n_rows": 3080089,
      "mean_ic": 0.022026595480779933,
      "shuffle_ic": 0.0017610823044753312,
      "edge_vs_shuffle": 0.020265513176304602,
      "nw_t": 0.5782842232091644,
      "net_per_period": -0.008634063813914326,
      "gross_per_period": -0.006601199158650781,
      "sharpe_net": -0.5160533393341425,
      "breakeven_cost_bps": -21.255895313897504,
      "cost_used_bps": 1.1837841719388962,
      "predict_zero_pnl": 0.0,
      "notes": ""
    },
    {
      "name": "probe_ret_15m_runup_h15",
      "signal": "feature",
      "label": "fwd_max_runup",
      "horizon": 15,
      "n_test_ts": 147,
      "n_rows": 3080089,
      "mean_ic": 0.015298947212989319,
      "shuffle_ic": 0.015671611228522488,
      "edge_vs_shuffle": -0.0003726640155331685,
      "nw_t": 0.42646221328588096,
      "net_per_period": -0.09706937135750755,
      "gross_per_period": -0.09513602281910637,
      "sharpe_net": -5.834098868086375,
      "breakeven_cost_bps": -309.41405703615413,
      "cost_used_bps": 1.1837841719388962,
      "predict_zero_pnl": 0.0,
      "notes": ""
    },
    {
      "name": "probe_ret_30m_runup_h15",
      "signal": "feature",
      "label": "fwd_max_runup",
      "horizon": 15,
      "n_test_ts": 147,
      "n_rows": 3080089,
      "mean_ic": 0.009127079842968783,
      "shuffle_ic": 0.011965618204122388,
      "edge_vs_shuffle": -0.002838538361153605,
      "nw_t": 0.22682120624113566,
      "net_per_period": -0.06695287326107137,
      "gross_per_period": -0.06500923230970249,
      "sharpe_net": -4.013009501480581,
      "breakeven_cost_bps": -207.26980293690983,
      "cost_used_bps": 1.1837841719388962,
      "predict_zero_pnl": 0.0,
      "notes": ""
    },
    {
      "name": "probe_ret_60m_runup_h15",
      "signal": "feature",
      "label": "fwd_max_runup",
      "horizon": 15,
      "n_test_ts": 147,
      "n_rows": 3080089,
      "mean_ic": 0.028142160144468402,
      "shuffle_ic": 0.011743266056795907,
      "edge_vs_shuffle": 0.016398894087672495,
      "nw_t": 0.6792891916194503,
      "net_per_period": 0.06660964720586461,
      "gross_per_period": 0.06817800180250586,
      "sharpe_net": 3.9815150865138,
      "breakeven_cost_bps": 295.9094955444555,
      "cost_used_bps": 1.1837841719388962,
      "predict_zero_pnl": 0.0,
      "notes": ""
    },
    {
      "name": "probe_realized_vol_5m_runup_h15",
      "signal": "feature",
      "label": "fwd_max_runup",
      "horizon": 15,
      "n_test_ts": 147,
      "n_rows": 3080089,
      "mean_ic": 0.3093694638261654,
      "shuffle_ic": 0.010987230393712064,
      "edge_vs_shuffle": 0.29838223343245335,
      "nw_t": 7.629166466218491,
      "net_per_period": 0.2209890004167692,
      "gross_per_period": 0.22224228001065183,
      "sharpe_net": 13.5264238914144,
      "breakeven_cost_bps": 1098.215876900086,
      "cost_used_bps": 1.1837841719388962,
      "predict_zero_pnl": 0.0,
      "notes": ""
    },
    {
      "name": "probe_realized_vol_30m_runup_h15",
      "signal": "feature",
      "label": "fwd_max_runup",
      "horizon": 15,
      "n_test_ts": 147,
      "n_rows": 3080089,
      "mean_ic": 0.33463345013952545,
      "shuffle_ic": 0.005766961467430387,
      "edge_vs_shuffle": 0.32886648867209506,
      "nw_t": 7.836856799677486,
      "net_per_period": 0.2231475373736413,
      "gross_per_period": 0.22403470496290034,
      "sharpe_net": 13.66427261320229,
      "breakeven_cost_bps": 1760.8910378846012,
      "cost_used_bps": 1.1837841719388962,
      "predict_zero_pnl": 0.0,
      "notes": ""
    },
    {
      "name": "probe_peak_trades_per_second_1m_runup_h15",
      "signal": "feature",
      "label": "fwd_max_runup",
      "horizon": 15,
      "n_test_ts": 147,
      "n_rows": 3080089,
      "mean_ic": 0.0661774954414801,
      "shuffle_ic": -0.0009948298125209876,
      "edge_vs_shuffle": 0.06717232525400109,
      "nw_t": 2.2151759874636157,
      "net_per_period": 0.13043207837980303,
      "gross_per_period": 0.13196266679879112,
      "sharpe_net": 7.856460303701036,
      "breakeven_cost_bps": 521.2769691787753,
      "cost_used_bps": 1.1837841719388962,
      "predict_zero_pnl": 0.0,
      "notes": ""
    },
    {
      "name": "probe_inter_arrival_cv_1m_runup_h15",
      "signal": "feature",
      "label": "fwd_max_runup",
      "horizon": 15,
      "n_test_ts": 147,
      "n_rows": 3080089,
      "mean_ic": -0.0032975318021400595,
      "shuffle_ic": -0.013347524520840521,
      "edge_vs_shuffle": 0.010049992718700461,
      "nw_t": -0.10852249002211924,
      "net_per_period": -0.03818453532044786,
      "gross_per_period": -0.03637053688413238,
      "sharpe_net": -2.2857141132422085,
      "breakeven_cost_bps": -134.62331817903785,
      "cost_used_bps": 1.1837841719388962,
      "predict_zero_pnl": 0.0,
      "notes": ""
    },
    {
      "name": "probe_max_runup_1m_runup_h15",
      "signal": "feature",
      "label": "fwd_max_runup",
      "horizon": 15,
      "n_test_ts": 147,
      "n_rows": 3080089,
      "mean_ic": 0.1543572244390092,
      "shuffle_ic": 0.014164707938976442,
      "edge_vs_shuffle": 0.14019251650003275,
      "nw_t": 4.254626254838795,
      "net_per_period": 0.11611847295978721,
      "gross_per_period": 0.11678204815368662,
      "sharpe_net": 6.984188012098682,
      "breakeven_cost_bps": 873.3192409167535,
      "cost_used_bps": 1.1837841719388962,
      "predict_zero_pnl": 0.0,
      "notes": ""
    },
    {
      "name": "probe_signed_volume_15m_runup_h15",
      "signal": "feature",
      "label": "fwd_max_runup",
      "horizon": 15,
      "n_test_ts": 147,
      "n_rows": 3080089,
      "mean_ic": -0.003909078560976429,
      "shuffle_ic": 0.010932282553629555,
      "edge_vs_shuffle": -0.014841361114605985,
      "nw_t": -0.12446594747553659,
      "net_per_period": -0.0011128260502979903,
      "gross_per_period": -0.00010900994792021766,
      "sharpe_net": -0.06652969218807857,
      "breakeven_cost_bps": -0.43485155043518886,
      "cost_used_bps": 1.1837841719388962,
      "predict_zero_pnl": 0.0,
      "notes": ""
    },
    {
      "name": "probe_trade_freq_15m_runup_h15",
      "signal": "feature",
      "label": "fwd_max_runup",
      "horizon": 15,
      "n_test_ts": 147,
      "n_rows": 3080089,
      "mean_ic": 0.061814735630301945,
      "shuffle_ic": -0.00593748400864393,
      "edge_vs_shuffle": 0.06775221963894587,
      "nw_t": 1.6493979049745922,
      "net_per_period": 0.019330203972714365,
      "gross_per_period": 0.01991926046190992,
      "sharpe_net": 1.1539934566680081,
      "breakeven_cost_bps": 247.58250906649658,
      "cost_used_bps": 1.1837841719388962,
      "predict_zero_pnl": 0.0,
      "notes": ""
    },
    {
      "name": "probe_trade_rate_accel_1m_runup_h15",
      "signal": "feature",
      "label": "fwd_max_runup",
      "horizon": 15,
      "n_test_ts": 147,
      "n_rows": 3080089,
      "mean_ic": -0.020923294355874658,
      "shuffle_ic": -0.004137315326440204,
      "edge_vs_shuffle": -0.016785979029434454,
      "nw_t": -0.7359257168435428,
      "net_per_period": -0.05607223082642643,
      "gross_per_period": -0.054708335384493156,
      "sharpe_net": -3.3606237403271573,
      "breakeven_cost_bps": -176.23248948161395,
      "cost_used_bps": 1.1837841719388962,
      "predict_zero_pnl": 0.0,
      "notes": ""
    },
    {
      "name": "probe_spread_bps_15m_runup_h15",
      "signal": "feature",
      "label": "fwd_max_runup",
      "horizon": 15,
      "n_test_ts": 147,
      "n_rows": 3080089,
      "mean_ic": 0.23583210903989818,
      "shuffle_ic": 0.015697014714691874,
      "edge_vs_shuffle": 0.2201350943252063,
      "nw_t": 7.169924150698985,
      "net_per_period": 0.22839338107459065,
      "gross_per_period": 0.22917238614710678,
      "sharpe_net": 13.650962543267958,
      "breakeven_cost_bps": 3054.4095625685723,
      "cost_used_bps": 1.1837841719388962,
      "predict_zero_pnl": 0.0,
      "notes": ""
    },
    {
      "name": "probe_quote_imbalance_15m_runup_h15",
      "signal": "feature",
      "label": "fwd_max_runup",
      "horizon": 15,
      "n_test_ts": 147,
      "n_rows": 3080089,
      "mean_ic": 0.003839075969245381,
      "shuffle_ic": -0.009656337675767379,
      "edge_vs_shuffle": 0.01349541364501276,
      "nw_t": 0.12821725672602413,
      "net_per_period": 0.034911571100514086,
      "gross_per_period": 0.03639696985882483,
      "sharpe_net": 2.0343647579955473,
      "breakeven_cost_bps": 165.88431302949752,
      "cost_used_bps": 1.1837841719388962,
      "predict_zero_pnl": 0.0,
      "notes": ""
    },
    {
      "name": "probe_book_depth_1m_runup_h15",
      "signal": "feature",
      "label": "fwd_max_runup",
      "horizon": 15,
      "n_test_ts": 147,
      "n_rows": 3080089,
      "mean_ic": 0.0014215016126379288,
      "shuffle_ic": -0.011430246297082093,
      "edge_vs_shuffle": 0.012851747909720022,
      "nw_t": 0.04942427439031855,
      "net_per_period": 0.022119089137751798,
      "gross_per_period": 0.022733882893883017,
      "sharpe_net": 1.2914309744391423,
      "breakeven_cost_bps": 215.14797149062625,
      "cost_used_bps": 1.1837841719388962,
      "predict_zero_pnl": 0.0,
      "notes": ""
    },
    {
      "name": "composite_up_h5_b30",
      "signal": "composite",
      "label": "up_move_start",
      "horizon": 5,
      "n_test_ts": 147,
      "n_rows": 3080089,
      "mean_ic": 0.009913217034047217,
      "shuffle_ic": -0.00409228170238165,
      "edge_vs_shuffle": 0.014005498736428867,
      "nw_t": 0.6159714120539826,
      "net_per_period": 0.053939221093332074,
      "gross_per_period": 0.05554223698420508,
      "sharpe_net": 4.817948441805721,
      "breakeven_cost_bps": 211.07553892364783,
      "cost_used_bps": 1.1837841719388962,
      "predict_zero_pnl": 0.0,
      "notes": ""
    },
    {
      "name": "composite_up_h5_b50",
      "signal": "composite",
      "label": "up_move_start",
      "horizon": 5,
      "n_test_ts": 147,
      "n_rows": 3080089,
      "mean_ic": 0.009814248816633304,
      "shuffle_ic": -0.006105294064941983,
      "edge_vs_shuffle": 0.015919542881575287,
      "nw_t": 0.5687676239307466,
      "net_per_period": 0.02274121420738886,
      "gross_per_period": 0.024344230098261872,
      "sharpe_net": 2.5523713140724333,
      "breakeven_cost_bps": 92.51466571526774,
      "cost_used_bps": 1.1837841719388962,
      "predict_zero_pnl": 0.0,
      "notes": ""
    },
    {
      "name": "composite_up_h15_b30",
      "signal": "composite",
      "label": "up_move_start",
      "horizon": 15,
      "n_test_ts": 147,
      "n_rows": 3080089,
      "mean_ic": 0.008771871405604356,
      "shuffle_ic": 0.0022634348980206946,
      "edge_vs_shuffle": 0.006508436507583662,
      "nw_t": 0.4779085060118757,
      "net_per_period": 0.1075906516195706,
      "gross_per_period": 0.10918653175552641,
      "sharpe_net": 4.597928948231194,
      "breakeven_cost_bps": 411.6556748134527,
      "cost_used_bps": 1.1837841719388962,
      "predict_zero_pnl": 0.0,
      "notes": ""
    },
    {
      "name": "composite_up_h15_b50",
      "signal": "composite",
      "label": "up_move_start",
      "horizon": 15,
      "n_test_ts": 147,
      "n_rows": 3080089,
      "mean_ic": 0.006392005617816706,
      "shuffle_ic": -0.0036641102533364577,
      "edge_vs_shuffle": 0.010056115871153164,
      "nw_t": 0.35431238488316535,
      "net_per_period": 0.05934278104280142,
      "gross_per_period": 0.060938661178757215,
      "sharpe_net": 7.050393197363884,
      "breakeven_cost_bps": 229.75128238286547,
      "cost_used_bps": 1.1837841719388962,
      "predict_zero_pnl": 0.0,
      "notes": ""
    },
    {
      "name": "composite_up_h30_b30",
      "signal": "composite",
      "label": "up_move_start",
      "horizon": 30,
      "n_test_ts": 147,
      "n_rows": 3080089,
      "mean_ic": 0.0011751359067787377,
      "shuffle_ic": -0.00018813101724623888,
      "edge_vs_shuffle": 0.0013632669240249767,
      "nw_t": 0.06251619842288109,
      "net_per_period": 0.0008704761497061431,
      "gross_per_period": 0.0022866289372892013,
      "sharpe_net": 0.0841756694464612,
      "breakeven_cost_bps": 8.756184054989088,
      "cost_used_bps": 1.1837841719388962,
      "predict_zero_pnl": 0.0,
      "notes": ""
    },
    {
      "name": "composite_up_h30_b50",
      "signal": "composite",
      "label": "up_move_start",
      "horizon": 30,
      "n_test_ts": 147,
      "n_rows": 3080089,
      "mean_ic": 0.007371429965109298,
      "shuffle_ic": -0.006391166177807539,
      "edge_vs_shuffle": 0.013762596142916837,
      "nw_t": 0.3944513720387812,
      "net_per_period": 0.0361988932308243,
      "gross_per_period": 0.03761504601840736,
      "sharpe_net": 4.163344616814976,
      "breakeven_cost_bps": 144.0392277045705,
      "cost_used_bps": 1.1837841719388962,
      "predict_zero_pnl": 0.0,
      "notes": ""
    },
    {
      "name": "ridge_up_h5_b50",
      "signal": "ridge",
      "label": "up_move_start",
      "horizon": 5,
      "n_test_ts": 147,
      "n_rows": 3080089,
      "mean_ic": -0.003296802311856679,
      "shuffle_ic": -0.0019031089590158823,
      "edge_vs_shuffle": -0.0013936933528407968,
      "nw_t": -0.20041003869038873,
      "net_per_period": -0.024463213519874467,
      "gross_per_period": -0.022563428782162585,
      "sharpe_net": -2.997088523703219,
      "breakeven_cost_bps": -82.83669940778697,
      "cost_used_bps": 1.1837841719388962,
      "predict_zero_pnl": 0.0,
      "notes": ""
    },
    {
      "name": "ridge_up_h15_b50",
      "signal": "ridge",
      "label": "up_move_start",
      "horizon": 15,
      "n_test_ts": 147,
      "n_rows": 3080089,
      "mean_ic": -0.0043148585303549435,
      "shuffle_ic": 0.0004278916684142965,
      "edge_vs_shuffle": -0.00474275019876924,
      "nw_t": -0.2598189294084643,
      "net_per_period": -0.01995895425197503,
      "gross_per_period": -0.01817870005144915,
      "sharpe_net": -2.5196201484671583,
      "breakeven_cost_bps": -74.70049330514512,
      "cost_used_bps": 1.1837841719388962,
      "predict_zero_pnl": 0.0,
      "notes": ""
    },
    {
      "name": "ridge_up_h30_b50",
      "signal": "ridge",
      "label": "up_move_start",
      "horizon": 30,
      "n_test_ts": 147,
      "n_rows": 3080089,
      "mean_ic": 0.0016694178259297418,
      "shuffle_ic": -0.0034960760477710986,
      "edge_vs_shuffle": 0.00516549387370084,
      "nw_t": 0.09405990885144584,
      "net_per_period": -0.039521901216635,
      "gross_per_period": -0.037958040359000744,
      "sharpe_net": -4.8909249101416075,
      "breakeven_cost_bps": -162.58570029383313,
      "cost_used_bps": 1.1837841719388962,
      "predict_zero_pnl": 0.0,
      "notes": ""
    },
    {
      "name": "gbm_up_h5_b50",
      "signal": "gbm",
      "label": "up_move_start",
      "horizon": 5,
      "n_test_ts": 147,
      "n_rows": 3080089,
      "mean_ic": -0.018707710793038245,
      "shuffle_ic": 0.0035941079926317884,
      "edge_vs_shuffle": -0.022301818785670034,
      "nw_t": -1.6866041772410805,
      "net_per_period": -0.04024289889683455,
      "gross_per_period": -0.03832990984650436,
      "sharpe_net": -5.500908924681028,
      "breakeven_cost_bps": -127.07400330780035,
      "cost_used_bps": 1.1837841719388962,
      "predict_zero_pnl": 0.0,
      "notes": ""
    },
    {
      "name": "gbm_up_h15_b50",
      "signal": "gbm",
      "label": "up_move_start",
      "horizon": 15,
      "n_test_ts": 147,
      "n_rows": 3080089,
      "mean_ic": -0.01862517935940088,
      "shuffle_ic": 0.004321737591887734,
      "edge_vs_shuffle": -0.022946916951288615,
      "nw_t": -1.5915987002337484,
      "net_per_period": -0.026224613099960468,
      "gross_per_period": -0.024466929628994456,
      "sharpe_net": -3.6041581432482896,
      "breakeven_cost_bps": -90.70487008858605,
      "cost_used_bps": 1.1837841719388962,
      "predict_zero_pnl": 0.0,
      "notes": ""
    },
    {
      "name": "gbm_up_h30_b50",
      "signal": "gbm",
      "label": "up_move_start",
      "horizon": 30,
      "n_test_ts": 147,
      "n_rows": 3080089,
      "mean_ic": -0.01525744435397262,
      "shuffle_ic": -0.0028264003616367142,
      "edge_vs_shuffle": -0.012431043992335907,
      "nw_t": -1.312603093718192,
      "net_per_period": 0.023267972522670335,
      "gross_per_period": 0.024809923969587835,
      "sharpe_net": 2.994883699998699,
      "breakeven_cost_bps": 95.24645569064809,
      "cost_used_bps": 1.1837841719388962,
      "predict_zero_pnl": 0.0,
      "notes": ""
    },
    {
      "name": "composite_runup_h5",
      "signal": "composite",
      "label": "fwd_max_runup",
      "horizon": 5,
      "n_test_ts": 147,
      "n_rows": 3080089,
      "mean_ic": 0.11154694263651733,
      "shuffle_ic": -0.004170174617580456,
      "edge_vs_shuffle": 0.11571711725409779,
      "nw_t": 3.312624379852164,
      "net_per_period": 0.0687609637504848,
      "gross_per_period": 0.0703639796413578,
      "sharpe_net": 4.111155841112331,
      "breakeven_cost_bps": 267.4021740938482,
      "cost_used_bps": 1.1837841719388962,
      "predict_zero_pnl": 0.0,
      "notes": ""
    },
    {
      "name": "composite_runup_h15",
      "signal": "composite",
      "label": "fwd_max_runup",
      "horizon": 15,
      "n_test_ts": 147,
      "n_rows": 3080089,
      "mean_ic": 0.12910249566939458,
      "shuffle_ic": 0.0061255983791048355,
      "edge_vs_shuffle": 0.12297689729028974,
      "nw_t": 3.73287603025675,
      "net_per_period": 0.06357474983555378,
      "gross_per_period": 0.06517062997150956,
      "sharpe_net": 3.801704495990766,
      "breakeven_cost_bps": 245.70667487642515,
      "cost_used_bps": 1.1837841719388962,
      "predict_zero_pnl": 0.0,
      "notes": ""
    },
    {
      "name": "composite_runup_h30",
      "signal": "composite",
      "label": "fwd_max_runup",
      "horizon": 30,
      "n_test_ts": 147,
      "n_rows": 3080089,
      "mean_ic": 0.10349697140657238,
      "shuffle_ic": 0.0033075273419137284,
      "edge_vs_shuffle": 0.10018944406465866,
      "nw_t": 2.658405823213688,
      "net_per_period": 0.020703477553173585,
      "gross_per_period": 0.02211963034075663,
      "sharpe_net": 1.2358040522838476,
      "breakeven_cost_bps": 84.70266046820781,
      "cost_used_bps": 1.1837841719388962,
      "predict_zero_pnl": 0.0,
      "notes": ""
    },
    {
      "name": "gbm_runup_h15",
      "signal": "gbm",
      "label": "fwd_max_runup",
      "horizon": 15,
      "n_test_ts": 147,
      "n_rows": 3080089,
      "mean_ic": 0.24875243802837405,
      "shuffle_ic": 0.003395268693766013,
      "edge_vs_shuffle": 0.24535716933460802,
      "nw_t": 6.754326481910796,
      "net_per_period": 0.045771919200898625,
      "gross_per_period": 0.04710851068366777,
      "sharpe_net": 2.732441657664269,
      "breakeven_cost_bps": 219.5410212567681,
      "cost_used_bps": 1.1837841719388962,
      "predict_zero_pnl": 0.0,
      "notes": ""
    },
    {
      "name": "ridge_runup_h15",
      "signal": "ridge",
      "label": "fwd_max_runup",
      "horizon": 15,
      "n_test_ts": 147,
      "n_rows": 3080089,
      "mean_ic": 0.23659460077377936,
      "shuffle_ic": 0.0002597063560138059,
      "edge_vs_shuffle": 0.23633489441776556,
      "nw_t": 5.448376231310401,
      "net_per_period": 0.029492366326018066,
      "gross_per_period": 0.03070032281665583,
      "sharpe_net": 1.7636762873659153,
      "breakeven_cost_bps": 180.77310725453117,
      "cost_used_bps": 1.1837841719388962,
      "predict_zero_pnl": 0.0,
      "notes": ""
    }
  ],
  "panel_load_seconds": 24.071,
  "eval_seconds": 1219.594,
  "total_seconds": 1243.664,
  "notes": []
}